{
    "svg/svg/text": {
        "tag": "text",
        "stroke": null,
        "stroke-width": 1,
        "stroke-opacity": 1,
        "fill": null,
        "opacity": 1,
        "level": 0,
        "layer": [
            "0",
            "0"
        ],
        "text_content": "hello2",
        "bbox": [
            [
                0.0,
                0.0
            ],
            [
                40.0,
                12.0
            ],
            [
                20.0,
                6.0
            ]
        ]
    },
    "svg/svg/text_1": {
        "tag": "text_1",
        "stroke": null,
        "stroke-width": 1,
        "stroke-opacity": 1,
        "fill": null,
        "opacity": 1,
        "level": 0,
        "layer": [
            "0",
            "1"
        ],
        "text_content": "hello",
        "bbox": [
            [
                0.0,
                0.0
            ],
            [
                40.0,
                12.0
            ],
            [
                20.0,
                6.0
            ]
        ]
    },
    "svg/svg/line": {
        "tag": "line",
        "stroke": "#808080",
        "stroke-width": 1,
        "stroke-opacity": 1,
        "fill": null,
        "opacity": 1,
        "level": 0,
        "layer": [
            "0",
            "2"
        ],
        "text_content": null,
        "bbox": [
            [
                300.0,
                400.0
            ],
            [
                350.0,
                450.0
            ],
            [
                325.0,
                425.0
            ]
        ]
    },
    "svg/svg/polyline": {
        "tag": "polyline",
        "stroke": "#000000",
        "stroke-width": 1,
        "stroke-opacity": 1,
        "fill": "none",
        "opacity": 1,
        "level": 0,
        "layer": [
            "0",
            "3"
        ],
        "text_content": null,
        "bbox": [
            [
                [
                    30.0,
                    450.0
                ],
                [
                    60.0,
                    480.0
                ],
                [
                    45.0,
                    465.0
                ]
            ],
            [
                [
                    60.0,
                    480.0
                ],
                [
                    30.0,
                    510.0
                ],
                [
                    45.0,
                    495.0
                ]
            ]
        ]
    },
    "svg/svg/polygon": {
        "tag": "polygon",
        "stroke": null,
        "stroke-width": 1,
        "stroke-opacity": 1,
        "fill": "#ffff00",
        "opacity": 1,
        "level": 0,
        "layer": [
            "0",
            "4"
        ],
        "text_content": null,
        "bbox": [
            [
                [
                    400.0,
                    10.0
                ],
                [
                    450.0,
                    30.0
                ],
                [
                    425.0,
                    20.0
                ]
            ],
            [
                [
                    450.0,
                    30.0
                ],
                [
                    400.0,
                    50.0
                ],
                [
                    425.0,
                    40.0
                ]
            ]
        ]
    },
    "svg/svg/ellipse": {
        "tag": "ellipse",
        "stroke": null,
        "stroke-width": 1,
        "stroke-opacity": 1,
        "fill": "#800080",
        "opacity": 1,
        "level": 0,
        "layer": [
            "0",
            "5"
        ],
        "text_content": null,
        "bbox": [
            [
                270.0,
                280.0
            ],
            [
                330.0,
                320.0
            ],
            [
                300.0,
                300.0
            ]
        ]
    },
    "svg/svg/g/path": {
        "tag": "path",
        "stroke": null,
        "stroke-width": 1,
        "stroke-opacity": 1,
        "fill": "#ffff00",
        "opacity": 1,
        "level": 0,
        "layer": [
            "0",
            "6",
            "0"
        ],
        "text_content": null,
        "bbox": [
            [
                [
                    150.0,
                    150.0
                ],
                [
                    200.0,
                    200.0
                ],
                [
                    175.0,
                    175.0
                ]
            ],
            [
                [
                    150.0,
                    200.0
                ],
                [
                    200.0,
                    250.0
                ],
                [
                    175.0,
                    225.0
                ]
            ],
            [
                [
                    150.0,
                    150.0
                ],
                [
                    150.0,
                    250.0
                ],
                [
                    150.0,
                    200.0
                ]
            ]
        ]
    },
    "svg/svg/g/path_1": {
        "tag": "path_1",
        "stroke": null,
        "stroke-width": 1,
        "stroke-opacity": 1,
        "fill": "#ffff00",
        "opacity": 1,
        "level": 0,
        "layer": [
            "0",
            "6",
            "1"
        ],
        "text_content": null,
        "bbox": [
            [
                [
                    10.0,
                    10.0
                ],
                [
                    50.0,
                    50.0
                ],
                [
                    30.0,
                    30.0
                ]
            ],
            [
                [
                    50.0,
                    43.7
                ],
                [
                    60.0,
                    50.0
                ],
                [
                    55.0,
                    46.85
                ]
            ],
            [
                [
                    60.0,
                    38.8
                ],
                [
                    70.0,
                    43.7
                ],
                [
                    65.0,
                    41.25
                ]
            ],
            [
                [
                    70.0,
                    35.3
                ],
                [
                    80.0,
                    38.8
                ],
                [
                    75.0,
                    37.05
                ]
            ],
            [
                [
                    80.0,
                    33.2
                ],
                [
                    90.0,
                    35.3
                ],
                [
                    85.0,
                    34.25
                ]
            ],
            [
                [
                    90.0,
                    32.5
                ],
                [
                    100.0,
                    33.2
                ],
                [
                    95.0,
                    32.85
                ]
            ],
            [
                [
                    100.0,
                    32.5
                ],
                [
                    110.0,
                    33.2
                ],
                [
                    105.0,
                    32.85
                ]
            ],
            [
                [
                    110.0,
                    33.2
                ],
                [
                    120.0,
                    35.3
                ],
                [
                    115.0,
                    34.25
                ]
            ],
            [
                [
                    120.0,
                    35.3
                ],
                [
                    130.0,
                    38.8
                ],
                [
                    125.0,
                    37.05
                ]
            ],
            [
                [
                    130.0,
                    38.8
                ],
                [
                    140.0,
                    43.7
                ],
                [
                    135.0,
                    41.25
                ]
            ],
            [
                [
                    140.0,
                    43.7
                ],
                [
                    150.0,
                    50.0
                ],
                [
                    145.0,
                    46.85
                ]
            ],
            [
                [
                    150.0,
                    50.0
                ],
                [
                    150.0,
                    50.0
                ],
                [
                    150.0,
                    50.0
                ]
            ],
            [
                [
                    50.0,
                    50.0
                ],
                [
                    200.0,
                    100.0
                ],
                [
                    125.0,
                    75.0
                ]
            ],
            [
                [
                    200.0,
                    100.0
                ],
                [
                    215.0,
                    112.2
                ],
                [
                    207.5,
                    106.1
                ]
            ],
            [
                [
                    215.0,
                    112.2
                ],
                [
                    230.0,
                    119.6
                ],
                [
                    222.5,
                    115.9
                ]
            ],
            [
                [
                    230.0,
                    119.6
                ],
                [
                    245.0,
                    123.4
                ],
                [
                    237.5,
                    121.5
                ]
            ],
            [
                [
                    245.0,
                    123.4
                ],
                [
                    260.0,
                    124.8
                ],
                [
                    252.5,
                    124.1
                ]
            ],
            [
                [
                    260.0,
                    124.8
                ],
                [
                    275.0,
                    125.0
                ],
                [
                    267.5,
                    124.9
                ]
            ],
            [
                [
                    275.0,
                    125.0
                ],
                [
                    290.0,
                    125.2
                ],
                [
                    282.5,
                    125.1
                ]
            ],
            [
                [
                    290.0,
                    125.2
                ],
                [
                    305.0,
                    126.6
                ],
                [
                    297.5,
                    125.9
                ]
            ],
            [
                [
                    305.0,
                    126.6
                ],
                [
                    320.0,
                    130.4
                ],
                [
                    312.5,
                    128.5
                ]
            ],
            [
                [
                    320.0,
                    130.4
                ],
                [
                    335.0,
                    137.8
                ],
                [
                    327.5,
                    134.1
                ]
            ],
            [
                [
                    335.0,
                    137.8
                ],
                [
                    350.0,
                    150.0
                ],
                [
                    342.5,
                    143.9
                ]
            ],
            [
                [
                    350.0,
                    150.0
                ],
                [
                    400.0,
                    200.0
                ],
                [
                    375.0,
                    175.0
                ]
            ]
        ]
    },
    "svg/svg/g/path_2": {
        "tag": "path_2",
        "stroke": null,
        "stroke-width": 1,
        "stroke-opacity": 1,
        "fill": "none",
        "opacity": 1,
        "level": 0,
        "layer": [
            "0",
            "6",
            "2"
        ],
        "text_content": null,
        "bbox": [
            [
                [
                    150.0,
                    150.0
                ],
                [
                    200.0,
                    200.0
                ],
                [
                    175.0,
                    175.0
                ]
            ],
            [
                [
                    150.0,
                    200.0
                ],
                [
                    200.0,
                    250.0
                ],
                [
                    175.0,
                    225.0
                ]
            ],
            [
                [
                    150.0,
                    150.0
                ],
                [
                    150.0,
                    250.0
                ],
                [
                    150.0,
                    200.0
                ]
            ]
        ]
    },
    "svg/svg/g_1/g_2/g_3/ellipse_1": {
        "tag": "ellipse_1",
        "stroke": null,
        "stroke-width": 1,
        "stroke-opacity": 1,
        "fill": "#ffa500",
        "opacity": 1,
        "level": 0,
        "layer": [
            "0",
            "7",
            "0",
            "0",
            "0"
        ],
        "text_content": null,
        "bbox": [
            [
                83.58757210636101,
                118.94291116568839
            ],
            [
                87.12310601229375,
                136.6205806953521
            ],
            [
                85.35533905932738,
                127.78174593052023
            ]
        ]
    },
    "svg/svg/g_1/g_2/circle": {
        "tag": "circle",
        "stroke": null,
        "stroke-width": 1,
        "stroke-opacity": 1,
        "fill": "#008000",
        "opacity": 1,
        "level": 0,
        "layer": [
            "0",
            "7",
            "0",
            "1"
        ],
        "text_content": null,
        "bbox": [
            [
                85.35533905932738,
                127.78174593052023
            ],
            [
                85.35533905932738,
                184.35028842544403
            ],
            [
                85.35533905932738,
                156.06601717798213
            ]
        ]
    },
    "svg/svg/g_1/rect": {
        "tag": "rect",
        "stroke": null,
        "stroke-width": 1,
        "stroke-opacity": 1,
        "fill": "#ff0000",
        "opacity": 1,
        "level": 0,
        "layer": [
            "0",
            "7",
            "1"
        ],
        "text_content": null,
        "bbox": [
            [
                155.49038105676658,
                170.49038105676658
            ],
            [
                182.94228634059948,
                272.9422863405995
            ],
            [
                169.21633369868303,
                221.71633369868303
            ]
        ]
    },
    "svg/svg/g_1/rect_1": {
        "tag": "rect_1",
        "stroke": null,
        "stroke-width": 1,
        "stroke-opacity": 1,
        "fill": "#ff0000",
        "opacity": 1,
        "level": 0,
        "layer": [
            "0",
            "7",
            "2"
        ],
        "text_content": null,
        "bbox": [
            [
                60.0,
                60.0
            ],
            [
                110.0,
                110.0
            ],
            [
                85.0,
                85.0
            ]
        ]
    }
}