[
    {
        "tag": "svg",
        "num": 1,
        "visible": false
    },
    {
        "tag": "g",
        "num": 9,
        "visible": false
    },
    {
        "tag": "path",
        "num": 6,
        "visible": true
    },
    {
        "tag": "polygon",
        "num": 2,
        "visible": true
    },
    {
        "tag": "polyline",
        "num": 2,
        "visible": true
    },
    {
        "tag": "line",
        "num": 2,
        "visible": true
    },
    {
        "tag": "ellipse",
        "num": 2,
        "visible": true
    },
    {
        "tag": "circle",
        "num": 3,
        "visible": true
    },
    {
        "tag": "rect",
        "num": 3,
        "visible": true
    },
    {
        "tag": "text",
        "num": 2,
        "visible": true
    }
]